tasks/__init__.py
tasks/async_task.py
django_serverless-1.1.dist-info/LICENSE
django_serverless-1.1.dist-info/METADATA
django_serverless-1.1.dist-info/WHEEL
django_serverless-1.1.dist-info/top_level.txt
django_serverless-1.1.dist-info/RECORD
