Metadata-Version: 2.1
Name: django-serverless
Version: 1.1
Summary: Django Serverless Helper Library
Home-page: https://github.com/pypa/sampleproject
Author: Mihai Onofrei
Author-email: onofreima@gmail.com
License: UNKNOWN
Project-URL: Bug Tracker, https://github.com/pypa/sampleproject/issues
Platform: UNKNOWN
Classifier: Programming Language :: Python :: 3
Classifier: License :: OSI Approved :: MIT License
Classifier: Operating System :: OS Independent
Requires-Python: >=3.6
License-File: LICENSE
